pollyxt_pipelines/__init__.py
pollyxt_pipelines/__main__.py
pollyxt_pipelines/config.py
pollyxt_pipelines/console.py
pollyxt_pipelines/enums.py
pollyxt_pipelines/locations/__init__.py
pollyxt_pipelines/locations/commands.py
pollyxt_pipelines/locations/locations.ini
pollyxt_pipelines/polly_to_scc/commands.py
pollyxt_pipelines/polly_to_scc/exceptions.py
pollyxt_pipelines/polly_to_scc/pollyxt.py
pollyxt_pipelines/polly_to_scc/scc_netcdf.py
pollyxt_pipelines/polly_to_scc/test_pollyxt.py
pollyxt_pipelines/qc_eldec/commands.py
pollyxt_pipelines/qc_eldec/constants.py
pollyxt_pipelines/qc_eldec/qc_eldec_file.py
pollyxt_pipelines/radiosondes/__init__.py
pollyxt_pipelines/radiosondes/commands.py
pollyxt_pipelines/radiosondes/exceptions.py
pollyxt_pipelines/radiosondes/noa_wrf.py
pollyxt_pipelines/scc_access/__init__.py
pollyxt_pipelines/scc_access/commands.py
pollyxt_pipelines/scc_access/constants.py
pollyxt_pipelines/scc_access/exceptions.py
pollyxt_pipelines/scc_access/types.py
pollyxt_pipelines/sun.py
pollyxt_pipelines/test_utils.py
pollyxt_pipelines/utils.py
pollyxt_pipelines-1.16.0.dist-info/COPYING
pollyxt_pipelines-1.16.0.dist-info/COPYING.LESSER
pollyxt_pipelines-1.16.0.dist-info/METADATA
pollyxt_pipelines-1.16.0.dist-info/WHEEL
pollyxt_pipelines-1.16.0.dist-info/entry_points.txt
pollyxt_pipelines-1.16.0.dist-info/RECORD
