Metadata-Version: 2.1
Name: pollyxt_pipelines
Version: 1.16.0
Summary: Tools and scripts related to the automated processing of PollyXT files
Author: Thanasis Georgiou
Author-email: ageorgiou@noa.gr
Requires-Python: >=3.9,<3.13
Classifier: Programming Language :: Python :: 3
Classifier: Programming Language :: Python :: 3.9
Classifier: Programming Language :: Python :: 3.10
Classifier: Programming Language :: Python :: 3.11
Classifier: Programming Language :: Python :: 3.12
Requires-Dist: astral (>=3.2,<4.0)
Requires-Dist: beautifulsoup4 (>=4.11.1,<5.0.0)
Requires-Dist: cleo (>=0.8.1,<0.9.0)
Requires-Dist: matplotlib (>=3.6.0,<4.0.0)
Requires-Dist: netCDF4 (>=1.5.7,<2.0.0)
Requires-Dist: numpy (>=1.26.4,<2.0.0)
Requires-Dist: pandas (>=1.5.0,<2.0.0)
Requires-Dist: requests (>=2.28.1,<3.0.0)
Requires-Dist: rich (>=12.5.1,<13.0.0)
